{"Macro":[{"Data":{"UnitName":"Speedwagon","CFrame":"-29.3887939453125, -126.85931396484375, -17.47442626953125","Index":1},"Event":"Summon","Time":0},{"Data":{"Index":1},"Event":"Upgrade","Time":11.06},{"Data":{"UnitName":"Ivankov2","CFrame":"3.139617919921875, -126.37451171875, 35.48162841796875","Index":2},"Event":"Summon","Time":15.37},{"Data":{"UnitName":"Ivankov2","CFrame":"-36.37969970703125, -126.37451171875, 42.11785888671875","Index":3},"Event":"Summon","Time":25.28},{"Data":{"Index":1},"Event":"Upgrade","Time":29.18},{"Data":{"Index":1},"Event":"Upgrade","Time":31.65},{"Data":{"Index":1},"Event":"Upgrade","Time":37.47},{"Data":{"Index":1},"Event":"Upgrade","Time":38.55},{"Data":{"Index":1},"Event":"Upgrade","Time":39.45},{"Data":{"Index":1},"Event":"Upgrade","Time":51.65},{"Data":{"Index":1},"Event":"Upgrade","Time":52.56},{"Data":{"UnitName":"Ivankov2","CFrame":"-56.307403564453125, -126.37451171875, -10.36102294921875","Index":4},"Event":"Summon","Time":54.69},{"Data":{"UnitName":"Ivankov2","CFrame":"-54.156494140625, -126.37451171875, -15.724365234375","Index":5},"Event":"Summon","Time":55.99},{"Data":{"UnitName":"Ivankov2","CFrame":"-42.958404541015625, -126.37451171875, -63.87957763671875","Index":6},"Event":"Summon","Time":59.75},{"Data":{"UnitName":"Ivankov2","CFrame":"-36.488250732421875, -126.37451171875, -63.83465576171875","Index":7},"Event":"Summon","Time":60.54},{"Data":{"UnitName":"Ivankov2","CFrame":"34.409881591796875, -126.37451171875, -61.54400634765625","Index":8},"Event":"Summon","Time":63.89},{"Data":{"UnitName":"Ivankov2","CFrame":"27.808349609375, -126.37451171875, -61.2747802734375","Index":9},"Event":"Summon","Time":64.5},{"Data":{"Index":1},"Event":"Upgrade","Time":64.85},{"Data":{"Index":1},"Event":"Upgrade","Time":65.73},{"Data":{"Index":1},"Event":"Upgrade","Time":77.98},{"Data":{"Index":1},"Event":"Upgrade","Time":78.85},{"Data":{"Index":2},"Event":"Upgrade","Time":79.97},{"Data":{"Index":2},"Event":"Upgrade","Time":80.32},{"Data":{"Index":3},"Event":"Upgrade","Time":83.97},{"Data":{"Index":1},"Event":"Upgrade","Time":91.07},{"Data":{"Index":1},"Event":"Upgrade","Time":91.78},{"Data":{"Index":5},"Event":"Upgrade","Time":93.75},{"Data":{"Index":1},"Event":"Upgrade","Time":104.26},{"Data":{"Index":8},"Event":"Upgrade","Time":108.26},{"Data":{"Index":8},"Event":"Upgrade","Time":108.53},{"Data":{"Index":8},"Event":"Upgrade","Time":108.87},{"Data":{"Index":8},"Event":"Upgrade","Time":109.26},{"Data":{"Index":1},"Event":"Upgrade","Time":117.4},{"Data":{"Index":7},"Event":"Upgrade","Time":123.27},{"Data":{"Index":7},"Event":"Upgrade","Time":123.6},{"Data":{"Index":7},"Event":"Upgrade","Time":123.88},{"Data":{"Index":7},"Event":"Upgrade","Time":124.19},{"Data":{"Index":5},"Event":"Upgrade","Time":128.05},{"Data":{"Index":5},"Event":"Upgrade","Time":128.38},{"Data":{"Index":1},"Event":"Upgrade","Time":130.62},{"Data":{"Index":5},"Event":"Upgrade","Time":134.65},{"Data":{"Index":4},"Event":"Upgrade","Time":137.15},{"Data":{"Index":4},"Event":"Upgrade","Time":137.46},{"Data":{"Index":4},"Event":"Upgrade","Time":137.76},{"Data":{"Index":4},"Event":"Upgrade","Time":138.69},{"Data":{"Index":6},"Event":"Upgrade","Time":143.79},{"Data":{"Index":6},"Event":"Upgrade","Time":144.11},{"Data":{"Index":6},"Event":"Upgrade","Time":144.42},{"Data":{"Index":6},"Event":"Upgrade","Time":144.69},{"Data":{"Index":6},"Event":"Upgrade","Time":145.03},{"Data":{"Index":4},"Event":"Upgrade","Time":148.52},{"Data":{"Index":5},"Event":"Upgrade","Time":150.05},{"Data":{"Index":9},"Event":"Upgrade","Time":157.35},{"Data":{"Index":9},"Event":"Upgrade","Time":157.64},{"Data":{"Index":9},"Event":"Upgrade","Time":157.98},{"Data":{"Index":9},"Event":"Upgrade","Time":158.29},{"Data":{"Index":9},"Event":"Upgrade","Time":158.58},{"Data":{"Index":8},"Event":"Upgrade","Time":160.52},{"Data":{"Index":2},"Event":"Upgrade","Time":169.34},{"Data":{"Index":2},"Event":"Upgrade","Time":169.67},{"Data":{"Index":2},"Event":"Upgrade","Time":169.99},{"Data":{"Index":3},"Event":"Upgrade","Time":173.87},{"Data":{"Index":3},"Event":"Upgrade","Time":174.21},{"Data":{"Index":3},"Event":"Upgrade","Time":174.52},{"Data":{"Index":3},"Event":"Upgrade","Time":174.83}],"Config":{"Macro Type":"Paid","Select Macro Must Wait Event":["ControlUnit","AttackControl"],"Timer Type":"First Enemy","Unit":{"RoyxLeader_MikasaS4":{"Orb":"N/A","Level":"N/A","Leader":true},"Ivankov2":{"Orb":"Prey Eye Orb","Level":175},"Speedwagon":{"Orb":"Universal Reduction Orb","Level":175}}}}